README.rst
setup.cfg
setup.py
signalz/__init__.py
signalz/misc.py
signalz.egg-info/PKG-INFO
signalz.egg-info/SOURCES.txt
signalz.egg-info/dependency_links.txt
signalz.egg-info/requires.txt
signalz.egg-info/top_level.txt
signalz/generators/__init__.py
signalz/generators/autoregressive_model.py
signalz/generators/brownian_noise.py
signalz/generators/card_dealer.py
signalz/generators/cosinus.py
signalz/generators/ecgsyn.py
signalz/generators/gaussian_white_noise.py
signalz/generators/levy_flight.py
signalz/generators/levy_noise.py
signalz/generators/levy_walk.py
signalz/generators/logistic_map.py
signalz/generators/lorem_ipsum.py
signalz/generators/mackey_glass.py
signalz/generators/random_steps.py
signalz/generators/sinus.py
signalz/generators/steps.py
signalz/generators/uniform_white_noise.py
tests/__init__.py