Metadata-Version: 1.2
Name: signalz
Version: 0.8
Summary: Synthetic data generators in Python
Home-page: http://matousc89.github.io/signalz/
Author: Matous Cejnek
Author-email: matousc@gmail.com
Maintainer: Matous Cejnek
License: MIT
Download-URL: https://github.com/matousc89/signalz/
Keywords: signals,data,artificial,generators,synthetic,noise
Platform: UNKNOWN
Classifier: Development Status :: 2 - Pre-Alpha
Classifier: License :: OSI Approved :: MIT License
Classifier: Topic :: Scientific/Engineering
Classifier: Topic :: Software Development :: Testing
Classifier: Intended Audience :: Science/Research
Classifier: Intended Audience :: Developers
Classifier: Intended Audience :: Education
Classifier: Programming Language :: Python
